license.md
lookout_sdk_ml-0.19.1-py3.5-nspkg.pth
requirements.txt
lookout/__main__.py
lookout/core/__init__.py
lookout/core/analyzer.py
lookout/core/bytes_to_unicode_converter.py
lookout/core/cmdline.py
lookout/core/data_requests.py
lookout/core/event_listener.py
lookout/core/garbage_exclusion.py
lookout/core/lib.py
lookout/core/manager.py
lookout/core/metrics.py
lookout/core/model_repository.py
lookout/core/modelforgecfg.py
lookout/core/package.py
lookout/core/ports.py
lookout/core/slogging.py
lookout/core/sqla_model_repository.py
lookout/core/api/__init__.py
lookout/core/api/event_pb2.py
lookout/core/api/event_pb2_grpc.py
lookout/core/api/service_analyzer_pb2.py
lookout/core/api/service_analyzer_pb2_grpc.py
lookout/core/api/service_data_pb2.py
lookout/core/api/service_data_pb2_grpc.py
lookout/core/api/version.py
lookout/core/container/Dockerfile.jinja2
lookout/core/container/analyzers.yml
lookout/core/container/docker-compose.yml.jinja2
lookout/core/container/lookout.yml.jinja2
lookout/core/container/wait-for-port.sh
lookout/core/container/wait-for-postgres.sh
lookout/core/examples/my_analyzer.py
lookout/core/examples/typos.py
lookout/core/helpers/__init__.py
lookout/core/helpers/analyzer_context_manager.py
lookout/core/helpers/server.py
lookout/core/langs/__init__.py
lookout/core/langs/javascript/__init__.py
lookout/core/langs/javascript/garbage.py
lookout_sdk_ml-0.19.1.dist-info/METADATA
lookout_sdk_ml-0.19.1.dist-info/WHEEL
lookout_sdk_ml-0.19.1.dist-info/entry_points.txt
lookout_sdk_ml-0.19.1.dist-info/namespace_packages.txt
lookout_sdk_ml-0.19.1.dist-info/top_level.txt
lookout_sdk_ml-0.19.1.dist-info/RECORD
