Metadata-Version: 2.1
Name: lookout-sdk-ml
Version: 0.19.1
Summary: Lookout Python SDK for stateful source code analyzers, typically using Machine Learning.
Home-page: https://github.com/src-d/lookout-sdk-ml
Author: source{d}
Author-email: machine-learning@sourced.tech
License: Apache-2.0
Download-URL: https://github.com/src-d/lookout-sdk-ml
Keywords: machine learning on source code,babelfish,lookout
Platform: UNKNOWN
Classifier: Development Status :: 4 - Beta
Classifier: Environment :: Console
Classifier: Intended Audience :: Developers
Classifier: License :: OSI Approved :: Apache Software License
Classifier: Operating System :: POSIX
Classifier: Programming Language :: Python :: 3.5
Classifier: Programming Language :: Python :: 3.6
Classifier: Programming Language :: Python :: 3.7
Classifier: Topic :: Software Development :: Quality Assurance
Requires-Dist: bblfsh (<3.0,>=2.12.7)
Requires-Dist: stringcase (<2.0,>=1.2.0)
Requires-Dist: sqlalchemy (<2.0,>=1.0.0)
Requires-Dist: sqlalchemy-utils (<2.0,>=0.33)
Requires-Dist: pympler (<2.0,>=0.5)
Requires-Dist: cachetools (<3.0,>=2.0)
Requires-Dist: configargparse (<2.0,>=0.13)
Requires-Dist: humanfriendly (<5.0,>=4.0)
Requires-Dist: psycopg2-binary (<3.0,>=2.7)
Requires-Dist: modelforge (<0.14.0,>=0.13.4)
Requires-Dist: requirements-parser (<2.0,>=0.2.0)
Requires-Dist: lookout-sdk (<0.5,>=0.4.1)
Requires-Dist: packaging (<20.0,>=16.8)
Requires-Dist: prometheus-client (==0.6.0)
Requires-Dist: typing ; python_version < "3.5"
Provides-Extra: test
Requires-Dist: docker (<4.0,>=3.4.0) ; extra == 'test'
